niti/.DS_Store
niti/__init__.py
niti/__main__.py
niti/__version__.py
niti/_version.py
niti/cli.py
niti/core/__init__.py
niti/core/config.py
niti/core/engine.py
niti/core/issue.py
niti/core/severity.py
niti/plugins/__init__.py
niti/plugins/base.py
niti/plugins/loader.py
niti/rules/__init__.py
niti/rules/base.py
niti/rules/base_registry.py
niti/rules/class_organization.py
niti/rules/class_traits.py
niti/rules/code_quality.py
niti/rules/documentation.py
niti/rules/file_organization.py
niti/rules/includes.py
niti/rules/logging.py
niti/rules/modern_cpp.py
niti/rules/namespace.py
niti/rules/naming.py
niti/rules/plugin_registry.py
niti/rules/registry.py
niti/rules/rule_definition.py
niti/rules/rule_id.py
niti/rules/safety.py
niti/rules/types.py
niti-0.2.9.dist-info/licenses/LICENSE
niti-0.2.9.dist-info/METADATA
niti-0.2.9.dist-info/WHEEL
niti-0.2.9.dist-info/entry_points.txt
niti-0.2.9.dist-info/top_level.txt
niti-0.2.9.dist-info/RECORD
