Metadata-Version: 2.4
Name: niti
Version: 0.2.9
Summary: A modern C++ linter written in Python
License: Apache 2.0
Project-URL: Repository, https://github.com/project-vajra/niti.git
Project-URL: Documentation, https://project-vajra.github.io/niti/
Project-URL: Bug Tracker, https://github.com/project-vajra/niti/issues
Keywords: c++,linter,static-analysis,code-quality
Requires-Python: >=3.8
License-File: LICENSE
Requires-Dist: pyyaml
Requires-Dist: tree-sitter
Requires-Dist: tree-sitter-cpp
Provides-Extra: dev
Requires-Dist: pytest>=7.0; extra == "dev"
Requires-Dist: pytest-cov>=4.0; extra == "dev"
Requires-Dist: black>=22.0; extra == "dev"
Requires-Dist: isort>=5.0; extra == "dev"
Requires-Dist: autoflake>=2.0; extra == "dev"
Requires-Dist: flake8>=5.0; extra == "dev"
Requires-Dist: flake8-pyproject>=1.2; extra == "dev"
Requires-Dist: mypy>=1.0; extra == "dev"
Requires-Dist: pre-commit>=2.20; extra == "dev"
Requires-Dist: twine>=4.0; extra == "dev"
Requires-Dist: build>=0.8; extra == "dev"
Dynamic: license-file
